setup.py
python/fastMapper/__init__.py
python/fastMapper/fastMapper.py
python/fastMapper.egg-info/PKG-INFO
python/fastMapper.egg-info/SOURCES.txt
python/fastMapper.egg-info/dependency_links.txt
python/fastMapper.egg-info/top_level.txt
src/MyRtree.hpp
src/bitMap.hpp
src/data.hpp
src/declare.hpp
src/fastMapper.hpp
src/fastMapper_pybind.cpp
src/fastMapper_to_lua.cpp
src/imageModel.hpp
src/main.cpp
src/svg.hpp
src/unit.hpp
src/wave.hpp
src/wfc.hpp
src/include/cmdline.h
src/include/rtree.hpp
src/include/simple_svg.hpp
src/include/stb_image.h
src/include/stb_image_write.h
src/include/test_bitmap.cpp
src/include/test_rtree.cpp