Metadata-Version: 2.1
Name: fastMapper
Version: 0.0.1
Summary:  fastMapper
Home-page: UNKNOWN
Author: f20500909
Author-email: me@lightgoing.com
License: ... 
Project-URL: Documentation, https://github.com/f20500909/fastMapper
Project-URL: Source, https://github.com/f20500909/fastMapper
Keywords: map
Platform: UNKNOWN
Requires-Python: >=3
